{
  "actions": "0x101",
  "activity": "0x102",
  "add": "0x103",
  "address": "0x104",
  "alert": "0x105",
  "anniversary": "0x106",
  "archive": "0x107",
  "aspect_ratio_fill": "0x108",
  "aspect_ratio_fit": "0x109",
  "attachment": "0x10a",
  "avatar": "0x10b",
  "basketball": "0x10c",
  "behance": "0x10d",
  "birthday": "0x10e",
  "bold": "0x10f",
  "book": "0x110",
  "bulb": "0x111",
  "bulk": "0x112",
  "caddy": "0x113",
  "calcul": "0x114",
  "camera": "0x115",
  "candidate_status": "0x116",
  "card_view": "0x117",
  "celebrate": "0x118",
  "check": "0x119",
  "chevron": "0x11a",
  "clock": "0x11b",
  "code": "0x11c",
  "coffee": "0x11d",
  "collapse": "0x11e",
  "comment": "0x11f",
  "comment_outline": "0x120",
  "compass": "0x121",
  "computer": "0x122",
  "contract": "0x123",
  "copy": "0x124",
  "cover_letter": "0x125",
  "create": "0x126",
  "cross": "0x127",
  "cross_target": "0x128",
  "crown": "0x129",
  "csv": "0x12a",
  "date": "0x12b",
  "department": "0x12c",
  "details": "0x12d",
  "diamond": "0x12e",
  "dish": "0x12f",
  "doc": "0x130",
  "docx": "0x131",
  "down": "0x132",
  "drag_and_drop": "0x133",
  "dribbble": "0x134",
  "earth": "0x135",
  "edit": "0x136",
  "education_level": "0x137",
  "email": "0x138",
  "email_outline": "0x139",
  "eot": "0x13a",
  "expand": "0x13b",
  "expand_text": "0x13c",
  "external_link": "0x13d",
  "eye": "0x13e",
  "facebook": "0x13f",
  "factory": "0x140",
  "female": "0x141",
  "filters": "0x142",
  "fingerprint": "0x143",
  "flag": "0x144",
  "flag_pointed": "0x145",
  "folder": "0x146",
  "gear": "0x147",
  "get": "0x148",
  "gif": "0x149",
  "github": "0x14a",
  "handshake": "0x14b",
  "hard_hat": "0x14c",
  "hashtag": "0x14d",
  "heading_1": "0x14e",
  "heading_2": "0x14f",
  "heart": "0x150",
  "heart_outline": "0x151",
  "heart_shiny": "0x152",
  "house": "0x153",
  "information": "0x154",
  "instagram": "0x155",
  "italic": "0x156",
  "jpeg": "0x157",
  "jpg": "0x158",
  "justice_hammer": "0x159",
  "left": "0x15a",
  "link": "0x15b",
  "linkedin": "0x15c",
  "location": "0x15d",
  "lock": "0x15e",
  "lock_rounded": "0x15f",
  "log_out": "0x160",
  "male": "0x161",
  "masonry": "0x162",
  "map": "0x163",
  "megaphone": "0x164",
  "mention": "0x165",
  "menu": "0x166",
  "mic": "0x167",
  "microship": "0x168",
  "money": "0x169",
  "more": "0x16a",
  "mountain": "0x16b",
  "music": "0x16c",
  "negative": "0x16d",
  "negative_outline": "0x16e",
  "negative_straight": "0x16f",
  "notification": "0x170",
  "offer_status": "0x171",
  "ordered_list": "0x172",
  "origine": "0x173",
  "paperplane": "0x174",
  "pdf": "0x175",
  "pencil": "0x176",
  "phone": "0x177",
  "phone_outline": "0x178",
  "pictures": "0x179",
  "piechart": "0x17a",
  "pin": "0x17b",
  "pinterest": "0x17c",
  "pizza": "0x17d",
  "play": "0x17e",
  "play_outline": "0x17f",
  "png": "0x180",
  "podcast": "0x181",
  "positive": "0x182",
  "positive_outline": "0x183",
  "positive_straight": "0x184",
  "print": "0x185",
  "promote": "0x186",
  "question": "0x187",
  "questions": "0x188",
  "quote": "0x189",
  "refresh": "0x18a",
  "refuse_candidate": "0x18b",
  "remote": "0x18c",
  "remove": "0x18d",
  "reset": "0x18e",
  "resume": "0x18f",
  "review": "0x190",
  "review_outline": "0x191",
  "right": "0x192",
  "salary": "0x193",
  "search": "0x194",
  "settings": "0x195",
  "share1": "0x196",
  "share2": "0x197",
  "shield": "0x198",
  "show": "0x199",
  "source": "0x19a",
  "spanner": "0x19b",
  "stackoverflow": "0x19c",
  "stackserver": "0x19d",
  "star": "0x19e",
  "strikethrough": "0x19f",
  "subtitle": "0x1a0",
  "suitcase": "0x1a1",
  "sun": "0x1a2",
  "svg": "0x1a3",
  "tag": "0x1a4",
  "tags": "0x1a5",
  "target": "0x1a6",
  "teepee": "0x1a7",
  "thumbup": "0x1a8",
  "trash": "0x1a9",
  "tree": "0x1aa",
  "trophy": "0x1ab",
  "ttf": "0x1ac",
  "twitch": "0x1ad",
  "twitter": "0x1ae",
  "txt": "0x1af",
  "unordered_list": "0x1b0",
  "up": "0x1b1",
  "update": "0x1b2",
  "upload": "0x1b3",
  "video": "0x1b4",
  "woff": "0x1b5",
  "woff2": "0x1b6",
  "write": "0x1b7",
  "xing": "0x1b8",
  "xls": "0x1b9",
  "xlsx": "0x1ba",
  "youtube": "0x1bb",
  "zip": "0x1bc",
  "burn": "0x1bd",
  "in_progress_candidate": "0x1be",
  "new_candidate": "0x1bf",
  "ppt": "0x1c0",
  "analytics": "0x1c1",
  "bar_chart": "0x1c2",
  "book_2": "0x1c3",
  "buoy": "0x1c4",
  "clipboard": "0x1c5",
  "credit_card": "0x1c6",
  "crescent_moon": "0x1c7",
  "crescent_moon_outline": "0x1c8",
  "headset": "0x1c9",
  "kanban": "0x1ca",
  "key": "0x1cb",
  "language": "0x1cc",
  "leaf": "0x1cd",
  "line_chart": "0x1ce",
  "office": "0x1cf",
  "puzzle": "0x1d0",
  "puzzle_outline": "0x1d1",
  "save": "0x1d2",
  "search_people": "0x1d3",
  "star_outline": "0x1d4",
  "type": "0x1d5",
  "video_camera": "0x1d6",
  "video_camera_2": "0x1d7",
  "heading": "0x1d8",
  "heading_3": "0x1d9",
  "heading_4": "0x1da",
  "heading_5": "0x1db",
  "heading_6": "0x1dc",
  "underline": "0x1dd",
  "code_block": "0x1de",
  "table": "0x1df",
  "table_column_add_after": "0x1e0",
  "table_column_add_before": "0x1e1",
  "table_column_remove": "0x1e2",
  "table_delete": "0x1e3",
  "table_divide": "0x1e4",
  "table_row_add_above": "0x1e5",
  "table_row_add_below": "0x1e6",
  "table_row_remove": "0x1e7",
  "table_merge_cells": "0x1e8",
  "npm": "0x1e9",
  "flag_fill": "0x1ea",
  "wttj": "0x1eb",
  "sound_on": "0x1EC",
  "fullscreen_off": "0x1ED",
  "fullscreen_on": "0x1EE",
  "user": "0x1EF",
  "user_outline": "0x1F0",
  "airplay": "0x1F1",
  "arrow_down": "0x1F2",
  "arrow_left": "0x1F3",
  "arrow_right": "0x1F4",
  "arrow_up": "0x1F5",
  "camera_off": "0x1F6",
  "camera_on": "0x1F7",
  "cast": "0x1F8",
  "cast_connected": "0x1F9",
  "cast_unavailable": "0x1FA",
  "control_backward": "0x1FB",
  "control_forward": "0x1FC",
  "control_pause": "0x1FD",
  "control_stop": "0x1FE",
  "duplicate": "0x1FF",
  "hide": "0x200",
  "home": "0x201",
  "microphone_off": "0x202",
  "microphone_on": "0x203",
  "more_android": "0x204",
  "pen": "0x205",
  "playlist": "0x206",
  "screenshare_off": "0x207",
  "screenshare_on": "0x208",
  "sound_off": "0x209",
  "watch_later": "0x20A",
  "unavailable": "0x20B",
  "avatar_accessory": "0x20C",
  "avatar_body": "0x20D",
  "avatar_bottom": "0x20E",
  "avatar_costume": "0x20F",
  "avatar_head": "0x210",
  "avatar_top": "0x211",
  "common_area": "0x212",
  "meeting_room": "0x213",
  "google": "0x214",
  "bookmark": "0x215",
  "bookmark_outline": "0x216",
  "equal": "0x217",
  "thumb_down": "0x219",
  "thumbdown": "0x21A"
}
