{
  "RadioTab": {
    "props": {
      "checked": {
        "defaultValue": null,
        "description": "",
        "name": "checked",
        "parent": {
          "fileName": "RadioTab/src/index.tsx",
          "name": "RadioTabsOptions"
        },
        "declarations": [
          {
            "fileName": "RadioTab/src/index.tsx",
            "name": "RadioTabsOptions"
          }
        ],
        "required": false,
        "type": {
          "name": "enum",
          "raw": "boolean",
          "value": [
            {
              "value": "false"
            },
            {
              "value": "true"
            }
          ]
        }
      },
      "disabled": {
        "defaultValue": null,
        "description": "",
        "name": "disabled",
        "parent": {
          "fileName": "RadioTab/src/index.tsx",
          "name": "RadioTabsOptions"
        },
        "declarations": [
          {
            "fileName": "RadioTab/src/index.tsx",
            "name": "RadioTabsOptions"
          }
        ],
        "required": false,
        "type": {
          "name": "enum",
          "raw": "boolean",
          "value": [
            {
              "value": "false"
            },
            {
              "value": "true"
            }
          ]
        }
      },
      "disabledIcon": {
        "defaultValue": null,
        "description": "",
        "name": "disabledIcon",
        "parent": {
          "fileName": "RadioTab/src/index.tsx",
          "name": "RadioTabsOptions"
        },
        "declarations": [
          {
            "fileName": "RadioTab/src/index.tsx",
            "name": "RadioTabsOptions"
          }
        ],
        "required": false,
        "type": {
          "name": "ReactElement<any, string | JSXElementConstructor<any>>"
        }
      },
      "hasIcon": {
        "defaultValue": null,
        "description": "",
        "name": "hasIcon",
        "declarations": [
          {
            "fileName": "packages/Utils/dist/types/field-styles.d.ts",
            "name": "TypeLiteral"
          }
        ],
        "required": false,
        "type": {
          "name": "enum",
          "raw": "boolean",
          "value": [
            {
              "value": "false"
            },
            {
              "value": "true"
            }
          ]
        }
      },
      "iconPlacement": {
        "defaultValue": null,
        "description": "",
        "name": "iconPlacement",
        "declarations": [
          {
            "fileName": "packages/Utils/dist/types/field-styles.d.ts",
            "name": "TypeLiteral"
          }
        ],
        "required": false,
        "type": {
          "name": "enum",
          "raw": "\"right\" | \"left\" | \"both\"",
          "value": [
            {
              "value": "\"right\""
            },
            {
              "value": "\"left\""
            },
            {
              "value": "\"both\""
            }
          ]
        }
      },
      "isClearable": {
        "defaultValue": null,
        "description": "",
        "name": "isClearable",
        "declarations": [
          {
            "fileName": "packages/Utils/dist/types/field-styles.d.ts",
            "name": "TypeLiteral"
          }
        ],
        "required": false,
        "type": {
          "name": "enum",
          "raw": "boolean",
          "value": [
            {
              "value": "false"
            },
            {
              "value": "true"
            }
          ]
        }
      },
      "label": {
        "defaultValue": null,
        "description": "",
        "name": "label",
        "parent": {
          "fileName": "RadioTab/src/index.tsx",
          "name": "RadioTabsOptions"
        },
        "declarations": [
          {
            "fileName": "RadioTab/src/index.tsx",
            "name": "RadioTabsOptions"
          }
        ],
        "required": true,
        "type": {
          "name": "ReactElement<any, string | JSXElementConstructor<any>>"
        }
      },
      "onChange": {
        "defaultValue": null,
        "description": "",
        "name": "onChange",
        "parent": {
          "fileName": "RadioTab/src/index.tsx",
          "name": "RadioTabsOptions"
        },
        "declarations": [
          {
            "fileName": "RadioTab/src/index.tsx",
            "name": "RadioTabsOptions"
          }
        ],
        "required": false,
        "type": {
          "name": "(event: ChangeEvent<HTMLInputElement>) => void"
        }
      },
      "size": {
        "defaultValue": null,
        "description": "",
        "name": "size",
        "declarations": [
          {
            "fileName": "packages/Utils/dist/types/field-styles.d.ts",
            "name": "TypeLiteral"
          }
        ],
        "required": false,
        "type": {
          "name": "enum",
          "raw": "Size",
          "value": [
            {
              "value": "\"xs\""
            },
            {
              "value": "\"sm\""
            },
            {
              "value": "\"md\""
            },
            {
              "value": "\"lg\""
            }
          ]
        }
      },
      "transparent": {
        "defaultValue": null,
        "description": "",
        "name": "transparent",
        "declarations": [
          {
            "fileName": "packages/Utils/dist/types/field-styles.d.ts",
            "name": "TypeLiteral"
          }
        ],
        "required": false,
        "type": {
          "name": "enum",
          "raw": "boolean",
          "value": [
            {
              "value": "false"
            },
            {
              "value": "true"
            }
          ]
        }
      },
      "value": {
        "defaultValue": null,
        "description": "",
        "name": "value",
        "parent": {
          "fileName": "RadioTab/src/index.tsx",
          "name": "RadioTabsOptions"
        },
        "declarations": [
          {
            "fileName": "RadioTab/src/index.tsx",
            "name": "RadioTabsOptions"
          }
        ],
        "required": true,
        "type": {
          "name": "enum",
          "raw": "string | number",
          "value": [
            {
              "value": "string"
            },
            {
              "value": "number"
            }
          ]
        }
      },
      "variant": {
        "defaultValue": null,
        "description": "",
        "name": "variant",
        "declarations": [
          {
            "fileName": "packages/Utils/dist/types/field-styles.d.ts",
            "name": "TypeLiteral"
          }
        ],
        "required": false,
        "type": {
          "name": "enum",
          "raw": "Variant",
          "value": [
            {
              "value": "\"danger\""
            },
            {
              "value": "\"info\""
            },
            {
              "value": "\"success\""
            },
            {
              "value": "\"warning\""
            }
          ]
        }
      }
    }
  }
}